python_viu_api/__init__.py
python_viu_api/viu_api_pb2.py
python_viu_api/viu_api_pb2_grpc.py
python_viu_api-0.3.54.dist-info/METADATA
python_viu_api-0.3.54.dist-info/WHEEL
python_viu_api-0.3.54.dist-info/top_level.txt
python_viu_api-0.3.54.dist-info/RECORD
