Metadata-Version: 2.1
Name: python-viu-api
Version: 0.3.54
Summary: gRPC client for VIU API
Home-page: https://github.com/VIU-one/python-viu-api
Author: Michael Weber
Author-email: info@searchviu.com
License: UNKNOWN
Platform: UNKNOWN
Classifier: Programming Language :: Python :: 3
Classifier: License :: OSI Approved :: MIT License
Classifier: Operating System :: OS Independent
Requires-Python: >=3.8
Requires-Dist: grpcio
Provides-Extra: dev
Requires-Dist: grpcio-tools; extra == "dev"
Requires-Dist: betterproto[compiler]; extra == "dev"
Requires-Dist: pytest; extra == "dev"
Requires-Dist: pytest-asyncio; extra == "dev"
Requires-Dist: twine; extra == "dev"
